deferred_tasks/__init__.py
deferred_tasks/apps.py
deferred_tasks/tasks.py
deferred_tasks/management/__init__.py
deferred_tasks/management/commands/__init__.py
deferred_tasks/management/commands/deferred_task.py
deferred_tasks/migrations/__init__.py
deferred_tasks-0.0.5.dist-info/METADATA
deferred_tasks-0.0.5.dist-info/WHEEL
deferred_tasks-0.0.5.dist-info/top_level.txt
deferred_tasks-0.0.5.dist-info/RECORD
