Metadata-Version: 2.1
Name: deferred-tasks
Version: 0.0.5
Summary: Run django code in one-off Heroku dynos.
Home-page: https://github.com/nickromano/deferred-tasks
Author: Nick Romano
Author-email: nick.r.romano@gmail.com
License: MIT
Platform: UNKNOWN
Classifier: Framework :: Django
Classifier: Intended Audience :: Developers
Classifier: License :: OSI Approved :: BSD License
Classifier: Operating System :: OS Independent
Classifier: Programming Language :: Python
Classifier: Programming Language :: Python :: 2
Classifier: Programming Language :: Python :: 2.7
Classifier: Programming Language :: Python :: 3
Classifier: Programming Language :: Python :: 3.5
Requires-Dist: Django (>=2.0)
Requires-Dist: requests
